wagtail_video/__init__.py
wagtail_video/admin.py
wagtail_video/admin_urls.py
wagtail_video/apps.py
wagtail_video/blocks.py
wagtail_video/edit_handlers.py
wagtail_video/forms.py
wagtail_video/models.py
wagtail_video/permissions.py
wagtail_video/wagtail_hooks.py
wagtail_video/widgets.py
wagtail_video/migrations/0001_initial.py
wagtail_video/migrations/__init__.py
wagtail_video/static/wagtail_video/js/.DS_Store
wagtail_video/static/wagtail_video/js/video-chooser.js
wagtail_video/templates/wagtail_video/chooser/chooser.html
wagtail_video/templates/wagtail_video/chooser/results.html
wagtail_video/templates/wagtail_video/homepage/.DS_Store
wagtail_video/templates/wagtail_video/homepage/site_summary_video.html
wagtail_video/templates/wagtail_video/permissions/includes/.DS_Store
wagtail_video/templates/wagtail_video/permissions/includes/video_permissions_formset.html
wagtail_video/templates/wagtail_video/video/_file_field.html
wagtail_video/templates/wagtail_video/video/_file_field_as_li.html
wagtail_video/templates/wagtail_video/video/_thumbnail_field.html
wagtail_video/templates/wagtail_video/video/_thumbnail_field_as_li.html
wagtail_video/templates/wagtail_video/video/add.html
wagtail_video/templates/wagtail_video/video/confirm_delete.html
wagtail_video/templates/wagtail_video/video/edit.html
wagtail_video/templates/wagtail_video/video/index.html
wagtail_video/templates/wagtail_video/video/list.html
wagtail_video/templates/wagtail_video/video/results.html
wagtail_video/templates/wagtail_video/video/usage.html
wagtail_video/templates/wagtail_video/widgets/.DS_Store
wagtail_video/templates/wagtail_video/widgets/video_chooser.html
wagtail_video/views/__init__.py
wagtail_video/views/chooser.py
wagtail_video/views/video.py
wagtail_video-1.0.1.dist-info/LICENSE
wagtail_video-1.0.1.dist-info/METADATA
wagtail_video-1.0.1.dist-info/WHEEL
wagtail_video-1.0.1.dist-info/top_level.txt
wagtail_video-1.0.1.dist-info/RECORD
